README.md
setup.py
linux_traffic_control/__init__.py
linux_traffic_control/bandCalc.py
linux_traffic_control/main.py
linux_traffic_control/test_case.py
linux_traffic_control/traffic_control.py
linux_traffic_control.egg-info/PKG-INFO
linux_traffic_control.egg-info/SOURCES.txt
linux_traffic_control.egg-info/dependency_links.txt
linux_traffic_control.egg-info/requires.txt
linux_traffic_control.egg-info/top_level.txt